humatron/__init__.py
humatron/py.typed
humatron/channels/__init__.py
humatron/channels/rest/__init__.py
humatron/channels/rest/client.py
humatron/worker/__init__.py
humatron/worker/beans.py
humatron/worker/client.py
humatron/worker/utils.py
humatron/worker/rest/__init__.py
humatron/worker/rest/utils.py
humatron/worker/rest/flask/__init__.py
humatron/worker/rest/flask/flask_server.py
humatron_python_sdk-1.3.14.dist-info/LICENSE.txt
humatron_python_sdk-1.3.14.dist-info/METADATA
humatron_python_sdk-1.3.14.dist-info/WHEEL
humatron_python_sdk-1.3.14.dist-info/top_level.txt
humatron_python_sdk-1.3.14.dist-info/RECORD
