Metadata-Version: 2.1
Name: humatron-python-sdk
Version: 1.3.14
Summary: SDK library for Humatron developers
Home-page: http://humatron.ai/build/python_worker_sdk
Author: Humatron
Author-email: worker_support@humatron.ai
Keywords: Humatron python
Classifier: Programming Language :: Python :: 3.11
Classifier: License :: OSI Approved :: MIT License
Classifier: Operating System :: OS Independent
Requires-Python: >=3.11
License-File: LICENSE.txt
